{
  "end_date": "2025-11-03",
  "num_trades": 1,
  "start_date": "2025-11-03",
  "successful_trades": 1,
  "symbol": "HSTM",
  "total_hedge_pnl": "0",
  "total_option_pnl": "32.123788215350300",
  "total_pnl": "32.123788215350300",
  "total_transaction_cost": "0",
  "trade_type": "straddle",
  "trades": [
    {
      "call_entry_price": "410.0",
      "call_exit_price": "371.177320440408200",
      "delta_pnl": "-32.70968504184565",
      "earnings_date": "2025-11-03",
      "earnings_time": "AfterMarketClose",
      "entry_debit": "503.578061172539500",
      "entry_surface_time": "2025-10-14T18:19:00Z",
      "entry_time": "2025-10-14T13:35:00Z",
      "exit_credit": "535.701849387889800",
      "exit_pricing_method": "Market",
      "exit_surface_time": "2025-10-31T19:55:00Z",
      "exit_time": "2025-10-31T19:55:00Z",
      "expected_move_pct": 19.995158275661684,
      "expiration": "2026-03-20",
      "failure_reason": null,
      "gamma_pnl": "2.174648928118524",
      "iv_change": 0.08223883089373873,
      "iv_entry": 0.350724744631158,
      "iv_exit": 0.4329635755248967,
      "net_delta": 0.5151131502652874,
      "net_gamma": 0.1078628025602846,
      "net_theta": -0.012615615311170593,
      "net_vega": 0.10331666839167997,
      "pnl": "32.123788215350300",
      "pnl_pct": "6.3791079660128043209136820400",
      "put_entry_price": "93.578061172539500",
      "put_exit_price": "164.524528947481600",
      "spot_at_entry": 25.185,
      "spot_at_exit": 24.55,
      "spot_move": -0.634999999999998,
      "spot_move_pct": -2.521342068691674,
      "strike": "22.5",
      "success": true,
      "symbol": "HSTM",
      "theta_pnl": "-21.76193641176927",
      "unexplained_pnl": "-0.545659462831772",
      "vega_pnl": "84.9664202036785"
    }
  ]
}