{
  "end_date": "2025-11-03",
  "num_trades": 1,
  "start_date": "2025-11-03",
  "successful_trades": 1,
  "symbol": "VTLE",
  "total_hedge_pnl": "0",
  "total_option_pnl": "-151.6809047080672200",
  "total_pnl": "-151.6809047080672200",
  "total_transaction_cost": "0",
  "trade_type": "straddle",
  "trades": [
    {
      "call_entry_price": "183.365739765096700",
      "call_exit_price": "105.00",
      "delta_pnl": "-0.4012446559243187",
      "earnings_date": "2025-11-03",
      "earnings_time": "AfterMarketClose",
      "entry_debit": "288.365739765096700",
      "entry_surface_time": "2025-10-14T19:38:00Z",
      "entry_time": "2025-10-14T13:35:00Z",
      "exit_credit": "136.6848350570294800",
      "exit_pricing_method": "Market",
      "exit_surface_time": "2025-10-31T19:55:00Z",
      "exit_time": "2025-10-31T19:55:00Z",
      "expected_move_pct": 18.361163166664333,
      "expiration": "2025-11-21",
      "failure_reason": null,
      "gamma_pnl": "0.002401194353678211",
      "iv_change": -0.29351748030162594,
      "iv_entry": 0.7130034375598222,
      "iv_exit": 0.41948595725819626,
      "net_delta": 0.26397674731862897,
      "net_gamma": 0.2078596220289282,
      "net_theta": -0.03587694577796598,
      "net_vega": 0.038340661840428274,
      "pnl": "-151.6809047080672200",
      "pnl_pct": "-52.600182265627943162726197710",
      "put_entry_price": "105.00",
      "put_exit_price": "31.6848350570294800",
      "spot_at_entry": 15.7052,
      "spot_at_exit": 15.69,
      "spot_move": -0.015200000000000102,
      "spot_move_pct": -0.09678323103176084,
      "strike": "15",
      "success": true,
      "symbol": "VTLE",
      "theta_pnl": "-61.8877314669913",
      "unexplained_pnl": "23.1422147854868",
      "vega_pnl": "-112.5365445649921"
    }
  ]
}