{
  "end_date": "2025-11-03",
  "num_trades": 1,
  "start_date": "2025-11-03",
  "successful_trades": 1,
  "symbol": "GTM",
  "total_hedge_pnl": "-115.31999999999999",
  "total_option_pnl": "42.646283451915800",
  "total_pnl": "-73.673716548084190",
  "total_transaction_cost": "1.00",
  "trade_type": "straddle",
  "trades": [
    {
      "call_entry_price": "76.730493176731200",
      "call_exit_price": "155.37677662864700",
      "delta_pnl": "14.39152993883896",
      "earnings_date": "2025-11-03",
      "earnings_time": "AfterMarketClose",
      "entry_debit": "141.730493176731200",
      "entry_surface_time": "2025-10-14T19:37:00Z",
      "entry_time": "2025-10-14T13:35:00Z",
      "exit_credit": "184.37677662864700",
      "exit_pricing_method": "Market",
      "exit_surface_time": "2025-10-31T19:55:00Z",
      "exit_time": "2025-10-31T19:55:00Z",
      "expected_move_pct": 14.081519441304641,
      "expiration": "2025-11-21",
      "failure_reason": null,
      "gamma_pnl": "30.22692700790536",
      "hedge_pnl": "-115.31999999999999",
      "hedge_position": {
        "avg_hedge_price": 10.0818,
        "cumulative_shares": -100,
        "hedges": [
          {
            "cost": "0.92",
            "delta_after": -0.002201824332895952,
            "delta_before": 0.9177981756671041,
            "shares": -92,
            "spot_price": 10.065,
            "timestamp": "2025-10-14T13:35:00Z"
          },
          {
            "cost": "0.08",
            "delta_after": -1.2502297930261363e-6,
            "delta_before": 0.07999874977020693,
            "shares": -8,
            "spot_price": 10.275,
            "timestamp": "2025-10-15T13:35:00Z"
          }
        ],
        "peak_long_shares": 0,
        "peak_short_shares": 100,
        "realized_pnl": "0",
        "realized_vol_metrics": {
          "entry_hv": 0.020875774082926297,
          "entry_iv": 0.5476668537275259,
          "exit_iv": 0.7510481533583422,
          "iv_premium_at_entry": 2523.456507777822,
          "num_observations": 15,
          "realized_vol": 0.311619790574364,
          "realized_vs_implied": -43.10048372410712
        },
        "spot_history": [
          [
            "2026-01-08T04:48:23.070197Z",
            10.065
          ],
          [
            "2025-10-14T13:35:00Z",
            10.065
          ],
          [
            "2025-10-15T13:35:00Z",
            10.275
          ],
          [
            "2025-10-16T13:35:00Z",
            10.38
          ],
          [
            "2025-10-17T13:35:00Z",
            10.16
          ],
          [
            "2025-10-20T13:35:00Z",
            10.3
          ],
          [
            "2025-10-21T13:35:00Z",
            10.495
          ],
          [
            "2025-10-22T13:35:00Z",
            10.835
          ],
          [
            "2025-10-23T13:35:00Z",
            10.935
          ],
          [
            "2025-10-24T13:35:00Z",
            11.19
          ],
          [
            "2025-10-27T13:35:00Z",
            11.37
          ],
          [
            "2025-10-28T13:35:00Z",
            11.5
          ],
          [
            "2025-10-29T13:35:00Z",
            11.18
          ],
          [
            "2025-10-30T13:35:00Z",
            10.8
          ],
          [
            "2025-10-31T13:35:00Z",
            11.035
          ]
        ],
        "total_cost": "1.00",
        "unrealized_pnl": "-115.31999999999999"
      },
      "iv_change": 0.2033812996308163,
      "iv_entry": 0.5476668537275259,
      "iv_exit": 0.7510481533583422,
      "net_delta": 0.12300452939178608,
      "net_gamma": 0.44162359570319765,
      "net_theta": -0.01835732132183064,
      "net_vega": 0.02569846544918389,
      "pnl": "42.646283451915800",
      "pnl_pct": "30.089702290626977544872757240",
      "put_entry_price": "65.00",
      "put_exit_price": "29.00",
      "spot_at_entry": 10.065,
      "spot_at_exit": 11.235,
      "spot_move": 1.17,
      "spot_move_pct": 11.624441132637854,
      "strike": "10",
      "success": true,
      "symbol": "GTM",
      "theta_pnl": "-31.66637928015786",
      "total_pnl_with_hedge": "-73.673716548084190",
      "unexplained_pnl": "-22.57166723039716",
      "vega_pnl": "52.2658730157265"
    }
  ]
}